pyanc350/__init__.py
pyanc350/v2/ANC350lib.py
pyanc350/v2/PyANC350.py
pyanc350/v2/__init__.py
pyanc350/v3/ANC350libv3.py
pyanc350/v3/PyANC350v3.py
pyanc350/v3/__init__.py
pyanc350/v4/ANC350libv4.py
pyanc350/v4/PyANC350v4.py
pyanc350/v4/__init__.py
pyanc350-0.9.1.dist-info/LICENSE
pyanc350-0.9.1.dist-info/METADATA
pyanc350-0.9.1.dist-info/WHEEL
pyanc350-0.9.1.dist-info/top_level.txt
pyanc350-0.9.1.dist-info/RECORD
