Metadata-Version: 2.1
Name: pyanc350
Version: 0.9.1
Summary: Windows wrapper for attocube systems AG's ANC350 control DLL
Home-page: https://github.com/Laukei/attocube-ANC350-Python-library
Author: Robert Heath
Author-email: rob@robheath.me.uk
License: UNKNOWN
Platform: UNKNOWN
Classifier: Programming Language :: Python :: 3
Classifier: License :: OSI Approved :: MIT License
Classifier: Operating System :: Microsoft :: Windows
Classifier: Development Status :: 3 - Alpha
